booking_properties_pkg/__init__.py
booking_properties_pkg/payment.py
21234191_cpp_pkg-1.0.0.dist-info/LICENSE
21234191_cpp_pkg-1.0.0.dist-info/METADATA
21234191_cpp_pkg-1.0.0.dist-info/WHEEL
21234191_cpp_pkg-1.0.0.dist-info/top_level.txt
21234191_cpp_pkg-1.0.0.dist-info/RECORD
